fw_nodes_mattermost/__init__.py
fw_nodes_mattermost/credentials.py
fw_nodes_mattermost/handlers/__init__.py
fw_nodes_mattermost/handlers/mattermost_ws.py
fw_nodes_mattermost/nodes/__init__.py
fw_nodes_mattermost/nodes/add_reaction.py
fw_nodes_mattermost/nodes/outgoing_webhook.py
fw_nodes_mattermost/nodes/post_message.py
fw_nodes_mattermost/nodes/slash_command.py
fw_nodes_mattermost/nodes/stream_trigger.py
fw_nodes_mattermost-0.0.1a1.dist-info/METADATA
fw_nodes_mattermost-0.0.1a1.dist-info/WHEEL
fw_nodes_mattermost-0.0.1a1.dist-info/entry_points.txt
fw_nodes_mattermost-0.0.1a1.dist-info/licenses/LICENSE
fw_nodes_mattermost-0.0.1a1.dist-info/RECORD
