Metadata-Version: 2.4
Name: fw-nodes-mattermost
Version: 0.0.1a1
Summary: Mattermost nodes for Flowire workflow automation
License-Expression: MIT
License-File: LICENSE
Requires-Python: >=3.11
Requires-Dist: flowire-sdk>=0.0.1a1
Requires-Dist: httpx>=0.26.0
Requires-Dist: websockets>=12.0
Provides-Extra: dev
Requires-Dist: pytest-asyncio>=0.23.0; extra == 'dev'
Requires-Dist: pytest>=8.0.0; extra == 'dev'
Requires-Dist: ruff>=0.4.0; extra == 'dev'
